netbox_access_lists/__init__.py
netbox_access_lists/filtersets.py
netbox_access_lists/forms.py
netbox_access_lists/graphql.py
netbox_access_lists/models.py
netbox_access_lists/navigation.py
netbox_access_lists/tables.py
netbox_access_lists/urls.py
netbox_access_lists/views.py
netbox_access_lists/api/__init__.py
netbox_access_lists/api/serializers.py
netbox_access_lists/api/urls.py
netbox_access_lists/api/views.py
netbox_access_lists/migrations/0001_initial.py
netbox_access_lists/migrations/__init__.py
netbox_access_lists-0.1.dist-info/METADATA
netbox_access_lists-0.1.dist-info/WHEEL
netbox_access_lists-0.1.dist-info/top_level.txt
netbox_access_lists-0.1.dist-info/RECORD
