Metadata-Version: 2.1
Name: netbox-access-lists
Version: 0.1
Summary: An example NetBox plugin
